corecipher/__init__.py
corecipher/aes_cipher.py
corecipher/cipher_base.py
corecipher/data_encoder.py
corecipher/dummy.py
corecipher/ivcipher.py
corecipher/ivfcipher.py
corecipher/keygen.py
corecipher/m12cipher.py
corecipher/m1cipher.py
corecipher/m2cipher.py
corecipher/mapping_cipher.py
corecipher/padding.py
corecipher/pseudo_random.py
corecipher/res_cipher.py
corecipher/result_encoder.py
corecipher/rsa_cipher.py
corecipher-0.1.0.dist-info/LICENSE
corecipher-0.1.0.dist-info/METADATA
corecipher-0.1.0.dist-info/WHEEL
corecipher-0.1.0.dist-info/top_level.txt
corecipher-0.1.0.dist-info/RECORD
