Metadata-Version: 2.1
Name: corecipher
Version: 0.1.0
Summary: 加解密工具基础包。提供AES/RSA等加解密方式。
Author: rRR0VrFP
Maintainer: rRR0VrFP
License: Apache License, Version 2.0
Keywords: cipher,corecipher,gcm aes cipher,ctr aes cipher,ecb aes cipher,aes cipher,rsa+aes cipher,rsa cipher
Classifier: Development Status :: 5 - Production/Stable
Classifier: Intended Audience :: Developers
Classifier: Topic :: Software Development :: Libraries :: Python Modules
Classifier: License :: OSI Approved :: Apache Software License
Classifier: Programming Language :: Python :: 3
Classifier: Programming Language :: Python :: 3 :: Only
License-File: LICENSE
Requires-Dist: msgpack
Requires-Dist: pycryptodome
Requires-Dist: rsa
